{
  "assetsByChunkName": {
    "vendors~app-account~app-checkout~app-confirmation~app-order": "chunk.0f342dd6d825db4f0f69.js",
    "vendors~app-account~app-confirmation~app-order": "chunk.dfc6d54aa26af2f5864a.js",
    "vendors~app-account~app-checkout": "chunk.239884f93c3abce6fb79.js",
    "vendors~app-cart~app-checkout": "chunk.e418b58bf6d5a351b0b1.js",
    "admin": [
      "admin.1c8b98a83d650f0f1957.js",
      "admin.1c8b98a83d650f0f1957.js.map"
    ],
    "app-account": "chunk.b50827cb829b839aa656.js",
    "app-cart": "chunk.c176445632a3d3b0d70c.js",
    "app-checkout": "chunk.ca61b33c5b49ce3a8791.js",
    "app-confirmation": "chunk.ee3d0a4c7fa0958c7f04.js",
    "app-order": "chunk.ced18cb63053f1ce7861.js",
    "checkout": [
      "checkout.a9f4ca06f1b1f3333ede.js",
      "checkout.a9f4ca06f1b1f3333ede.js.map"
    ],
    "storefront": [
      "storefront.f4c9c415012bc1d7cf0a.css",
      "storefront.400658f28f9d63e72893.js",
      "storefront.f4c9c415012bc1d7cf0a.css.map",
      "storefront.400658f28f9d63e72893.js.map"
    ],
    "vendors~app-cart": "chunk.8ea4ea8dff79a2eaf2db.js"
  }
}